charmonium/async_subprocess/__init__.py
charmonium/async_subprocess/py.typed
charmonium.async_subprocess-0.1.7.dist-info/WHEEL
charmonium.async_subprocess-0.1.7.dist-info/METADATA
charmonium.async_subprocess-0.1.7.dist-info/RECORD
