Metadata-Version: 2.1
Name: charmonium.async-subprocess
Version: 0.1.7
Summary: async clone of subprocess.run
Home-page: https://github.com/charmoniumQ/charmonium.async_subprocess.git
License: MIT
Keywords: async,subprocess,shell
Author: Samuel Grayson
Author-email: sam@samgrayson.me
Requires-Python: >=3.7,<4.0
Classifier: Development Status :: 4 - Beta
Classifier: License :: OSI Approved :: MIT License
Classifier: Operating System :: MacOS
Classifier: Operating System :: Microsoft :: Windows
Classifier: Operating System :: POSIX :: Linux
Classifier: Programming Language :: Python :: 3
Classifier: Programming Language :: Python :: 3.7
Classifier: Programming Language :: Python :: 3.8
Classifier: Programming Language :: Python :: 3.9
Classifier: Topic :: Software Development :: Libraries
Project-URL: Repository, https://github.com/charmoniumQ/charmonium.async_subprocess.git
